{
  "poll_interval_sec": 60,
  "expected_total_teams": 96,
  "capacity_per_region": 32,
  "qingflow_url": "https://qingflow.com/appView/e3bol1op1c02/shareView/e3bol20d1c02?exWsId=1SdM5_PB-NwUtnyPn2b8NA&qfVersion=mysql",
  "announcement_urls": {
    "teams_2026": "https://www.robomaster.com/zh-CN/resource/pages/announcement/1909",
    "rules_2026": "https://www.robomaster.com/zh-CN/resource/pages/announcement/1910",
    "ranking_2025": "https://www.robomaster.com/zh-CN/resource/pages/announcement/1884",
    "national_2025": "https://www.robomaster.com/zh-CN/resource/pages/announcement/1856",
    "regional_2025": "https://www.robomaster.com/zh-CN/resource/pages/announcement/1847"
  },
  "announcement_local_dir": "data/announcements",
  "announcement_local_only": false,
  "manual_top16_counts": null,
  "priority_schools": [
    "长沙理工大学",
    "齐鲁工业大学",
    "东北大学"
  ],
  "rmu_ranking_csv": "data/rmu_ranking.csv",
  "cache_file": ".cache/latest_qingflow_snapshot.json",
  "request_timeout_sec": 20
}
